binman/__init__.py
binman/config.py
binman/install.py
binman/main.py
binman/output.py
binman/state.py
binman/uninstall.py
github/__init__.py
github/asset.py
github/release.py
github/repository.py
binman-0.1.1.dist-info/LICENSE
binman-0.1.1.dist-info/METADATA
binman-0.1.1.dist-info/WHEEL
binman-0.1.1.dist-info/entry_points.txt
binman-0.1.1.dist-info/top_level.txt
binman-0.1.1.dist-info/RECORD
